<mockup version="5.3" minAllowVersion="5.3" ID="5CB4B189-906C-481D-A48E-57D64E17B692" platform="MtWeb" defaultW="1190" defaultH="2300" measureW="1190" measureH="2300" mobileScreenScale="0">
  <controls controlCount="14">
    <control controlID="EE8B47FA-67FD-4333-A343-CE6654C6192F" controlTypeID="Tab" x="8" y="59" w="1163" h="1247" zOrder="0">
      <links eventType="AtClick" animate="AmNone" animateAutoDelay="0" animateDuration="500">
        <link targetPageID="CE736454-07A6-4CE3-803B-4390F59DAE30" linkType="ltPageLink" isApplyIncludePage="False" title="Contacts">
          <area shape="0" alt="" ID="{0196451C-33D1-41AE-B644-1571B51EFDC8}" coords="(0,0,71,18)"/>
        </link>
        <link targetPageID="" linkType="ltPageLink" isApplyIncludePage="False" title="+John+Doe">
          <area shape="0" alt="" ID="{931232A1-AFBA-4A1C-9251-62BC946938AB}" coords="(70,0,149,18)"/>
        </link>
      </links>
      <font family="Arial" displayName="Arial" postScript="" weightStyle="Regular" weight="400" isBold="False" isItalic="False" useDefaultFontFamily="False"/>
      <text>Contacts%2C+John+Doe</text>
      <textSize>14</textSize>
      <lineSpacing>0</lineSpacing>
      <useDefaultTextSize>False</useDefaultTextSize>
      <selectedIndex>1</selectedIndex>
    </control>
    <control controlID="9D2B48FC-008A-433B-8423-80BB66DF8FA3" controlTypeID="Image" x="0" y="0" w="1190" h="50" zOrder="1">
      <URL>35CA1CC1026F6EB5A937F8673FF5E4BC.png</URL>
    </control>
    <control controlID="FFB5E101-E582-490C-BF5A-452A07167363" controlTypeID="__group__" x="18" y="86" w="1148" h="1199" zOrder="2">
      <groupChildrenDescriptors>
        <control controlID="563E8907-BAEB-4FCD-8C5F-76B07136AA3B" controlTypeID="__group__" x="0" y="0" w="1148" h="1199" zOrder="0">
          <groupChildrenDescriptors>
            <control controlID="53D3A207-B29C-4393-A662-4FB707790C86" controlTypeID="Tab" x="0" y="0" w="1148" h="1199" zOrder="0">
              <font family="Arial" displayName="Arial" postScript="" weightStyle="Regular" weight="400" isBold="False" isItalic="False"/>
              <text>Contact+Details%2C+Create+Order</text>
              <textSize>14</textSize>
              <lineSpacing>0</lineSpacing>
              <selectedIndex>1</selectedIndex>
            </control>
            <control controlID="53CD9019-E53E-4850-8521-897211EE3A76" controlTypeID="ButtonBar" x="827" y="45" w="311" h="29" zOrder="1">
              <color>4291611852</color>
              <borderColor>4288256409</borderColor>
              <font family="Arial" displayName="Arial" postScript="" weightStyle="Regular" weight="400" isBold="False" isItalic="False"/>
              <text>Save%2CSave+%26+Close%2CCancel</text>
              <textSize>14</textSize>
              <lineSpacing>0</lineSpacing>
              <selectedColor>4294967295</selectedColor>
            </control>
            <control controlID="50278E2F-9B61-4EF6-BB30-5F1EEC5F7634" controlTypeID="__group__" x="723" y="45" w="86" h="29" zOrder="2">
              <groupChildrenDescriptors>
                <control controlID="E2F5E35A-74C8-473A-8F08-8E59086FF0B3" controlTypeID="ButtonBar" x="0" y="0" w="86" h="29" zOrder="0">
                  <color>4291611852</color>
                  <font family="Arial" displayName="Arial" postScript="" weightStyle="Regular" weight="400" isBold="False" isItalic="False"/>
                  <text>Actions</text>
                  <textSize>14</textSize>
                  <lineSpacing>0</lineSpacing>
                  <selectedColor>4294967295</selectedColor>
                </control>
                <control controlID="12E41EE6-EC6D-4B9E-BDF2-4DB1B1C96575" controlTypeID="Image" x="67" y="11" w="9" h="8" zOrder="1">
                  <URL>493BC4B533238F3EDF06B73175E0D4BA.png</URL>
                </control>
              </groupChildrenDescriptors>
            </control>
          </groupChildrenDescriptors>
        </control>
        <control controlID="4799C8CF-DD62-4CDC-A888-45526D74D6E6" controlTypeID="Label" x="5" y="87" w="262" h="24" zOrder="1">
          <font family="Segoe+UI" displayName="Segoe+UI" postScript="" weightStyle="Regular" weight="400" isBold="False" isItalic="False" useDefaultFontFamily="False"/>
          <text>Edit+Contact%3A+John+Doe%3A+Overview</text>
          <textSize>18</textSize>
          <lineSpacing>0</lineSpacing>
          <useDefaultTextSize>False</useDefaultTextSize>
          <selectedIndex>-1</selectedIndex>
        </control>
      </groupChildrenDescriptors>
    </control>
    <control controlID="4FE88F70-BEB7-455F-B0B7-D331D6BD898C" controlTypeID="LinkBar" x="172" y="32" w="540" h="17" zOrder="3">
      <font family="Arial" displayName="Arial" postScript="" weightStyle="Regular" weight="400" isBold="False" isItalic="False"/>
      <text>Order+details+page+comments%2C+New+Note+Comments%2C+Page+navigation+link+comments</text>
      <textSize>14</textSize>
      <lineSpacing>0</lineSpacing>
      <useDefaultTextSize>False</useDefaultTextSize>
    </control>
    <control controlID="B3767646-1BC1-42F2-8686-33BF45BA895C" controlTypeID="Image" x="21" y="112" w="1142" h="1029" zOrder="4">
      <URL>236F4C73EF788DB332B07BD84CCE1FFF.png</URL>
    </control>
    <control controlID="EEAE0DBA-D958-45B2-BF0C-B760D2ADF472" controlTypeID="Image" x="68" y="245" w="1031" h="757" zOrder="5">
      <caption>Item+Details</caption>
      <URL>520DFC97FF26FFC716487FA1146C3F0E.png</URL>
    </control>
    <control controlID="4CC2F00C-D4A4-4082-93C6-A964717A50AF" controlTypeID="HotSpot" x="672" y="639" w="128" h="37" zOrder="6">
      <links eventType="AtClick" animate="AmNone" animateAutoDelay="0" animateDuration="500">
        <link targetPageID="2119E00D-0DD4-4B6E-98C8-9B364A406330" linkType="ltPageLink" isApplyIncludePage="False" title="Complete+Order">
          <area shape="0" alt="" ID="{7BC03128-665D-4811-966A-874BAA9AC3A2}" coords="(0,0,128,37)"/>
        </link>
      </links>
    </control>
  </controls>
  <param>
    <backgroundColor>4294967295</backgroundColor>
    <fontSize>14</fontSize>
    <fontFamily>Arial</fontFamily>
    <guideLines/>
    <remark>Hello+World</remark>
  </param>
</mockup>